iaa_explore.py
impute_annotation.py
validate_coordinates.py
validate_data.py
itallic-0.0.1.dist-info/LICENSE.txt
itallic-0.0.1.dist-info/METADATA
itallic-0.0.1.dist-info/WHEEL
itallic-0.0.1.dist-info/top_level.txt
itallic-0.0.1.dist-info/RECORD
