Metadata-Version: 2.1
Name: itallic
Version: 0.0.1
Summary: Detects potential corrupt entries in a dataframe with lat,lng and country tagged data.
Home-page: https://github.com/getiria-onsongo/itallic
Author: Getiria Onsongo
Author-email: gonsongo@macalester.edu
License: UNKNOWN
Keywords: sample,setuptools,development
Platform: UNKNOWN
Classifier: Development Status :: 3 - Alpha
Classifier: Intended Audience :: Developers
Classifier: Topic :: Software Development :: Build Tools
Classifier: License :: OSI Approved :: MIT License
Classifier: Programming Language :: Python :: 3
Classifier: Programming Language :: Python :: 3.6
Classifier: Programming Language :: Python :: 3.7
Classifier: Programming Language :: Python :: 3.8
Classifier: Programming Language :: Python :: 3.9
Classifier: Programming Language :: Python :: 3 :: Only
Requires-Python: >=3.6, <4
Requires-Dist: sridentify
Requires-Dist: geopandas
Requires-Dist: geocoder
Requires-Dist: psycopg2
Requires-Dist: geopy
Requires-Dist: xlrd
Requires-Dist: folium
Requires-Dist: country-converter
Requires-Dist: scikit-learn
